{"_id":"each","_rev":"69-8d65e59e6a74c2b6cccf2ef97861f2a3","name":"each","description":"Chained and parallel async iterator in one elegant function","dist-tags":{"latest":"0.6.1"},"versions":{"0.0.1":{"name":"each","version":"0.0.1","description":"Chained and parallel async iterator in one elegant function","author":{"name":"David Worms","email":"david@adaltas.com"},"contributors":[{"name":"David Worms","email":"david@adaltas.com"}],"dependencies":{"coffee-script":"latest"},"devDependencies":{"expresso":"latest"},"engines":{"node":">= 0.4.0"},"keywords":["array","object","each"],"repository":{"type":"git","url":"git://github.com/wdavidw/node-each.git"},"_npmJsonOpts":{"file":"/Users/wdavidw/.npm/each/0.0.1/package/package.json","wscript":false,"contributors":false,"serverjs":false},"_id":"each@0.0.1","_engineSupported":true,"_npmVersion":"1.0.27","_nodeVersion":"v0.4.11","_defaultsLoaded":true,"dist":{"shasum":"fa03805fd820031ce2cbf48f487db1829fb3551d","tarball":"https://registry.npmjs.org/each/-/each-0.0.1.tgz"},"maintainers":[{"name":"david","email":"david@adaltas.com"}],"directories":{}},"0.0.2":{"name":"each","version":"0.0.2","description":"Chained and parallel async iterator in one elegant function","author":{"name":"David Worms","email":"david@adaltas.com"},"contributors":[{"name":"David Worms","email":"david@adaltas.com"}],"dependencies":{"coffee-script":"latest"},"devDependencies":{"expresso":"latest"},"engines":{"node":">= 0.4.0"},"keywords":["control flow","asynchronous","array","object","each"],"repository":{"type":"git","url":"git://github.com/wdavidw/node-each.git"},"_npmUser":{"name":"david","email":"david@adaltas.com"},"_id":"each@0.0.2","_engineSupported":true,"_npmVersion":"1.0.103","_nodeVersion":"v0.5.10","_defaultsLoaded":true,"dist":{"shasum":"09da3e4b6969fcff54b1ff1e7f13eab39a0334ae","tarball":"https://registry.npmjs.org/each/-/each-0.0.2.tgz"},"maintainers":[{"name":"david","email":"david@adaltas.com"}],"directories":{}},"0.0.3":{"name":"each","version":"0.0.3","description":"Chained and parallel async iterator in one elegant function","author":{"name":"David Worms","email":"david@adaltas.com"},"contributors":[{"name":"David Worms","email":"david@adaltas.com"}],"dependencies":{"coffee-script":"latest"},"devDependencies":{"expresso":"latest"},"engines":{"node":">= 0.4.0"},"keywords":["control flow","asynchronous","array","object","each"],"repository":{"type":"git","url":"git://github.com/wdavidw/node-each.git"},"_npmUser":{"name":"david","email":"david@adaltas.com"},"_id":"each@0.0.3","_engineSupported":true,"_npmVersion":"1.0.105","_nodeVersion":"v0.4.11","_defaultsLoaded":true,"dist":{"shasum":"0d726e5f042b447f581c265a59b55b2cb745075d","tarball":"https://registry.npmjs.org/each/-/each-0.0.3.tgz"},"maintainers":[{"name":"david","email":"david@adaltas.com"}],"directories":{}},"0.0.4":{"name":"each","version":"0.0.4","description":"Chained and parallel async iterator in one elegant function","author":{"name":"David Worms","email":"david@adaltas.com"},"contributors":[{"name":"David Worms","email":"david@adaltas.com"}],"dependencies":{"coffee-script":"latest"},"devDependencies":{"expresso":"latest"},"engines":{"node":">= 0.4.0"},"keywords":["control flow","asynchronous","array","object","each"],"repository":{"type":"git","url":"git://github.com/wdavidw/node-each.git"},"_npmUser":{"name":"david","email":"david@adaltas.com"},"_id":"each@0.0.4","_engineSupported":true,"_npmVersion":"1.0.105","_nodeVersion":"v0.4.11","_defaultsLoaded":true,"dist":{"shasum":"c1f315637fe77243973a3a4bd2cecbc1082d4d77","tarball":"https://registry.npmjs.org/each/-/each-0.0.4.tgz"},"maintainers":[{"name":"david","email":"david@adaltas.com"}],"directories":{}},"0.0.5":{"name":"each","version":"0.0.5","description":"Chained and parallel async iterator in one elegant function","author":{"name":"David Worms","email":"david@adaltas.com"},"contributors":[{"name":"David Worms","email":"david@adaltas.com"}],"dependencies":{"coffee-script":"latest"},"engines":{"node":">= 0.4.0"},"keywords":["control flow","asynchronous","array","object","each"],"repository":{"type":"git","url":"git://github.com/wdavidw/node-each.git"},"_npmUser":{"name":"david","email":"david@adaltas.com"},"_id":"each@0.0.5","devDependencies":{},"_engineSupported":true,"_npmVersion":"1.0.105","_nodeVersion":"v0.6.1","_defaultsLoaded":true,"dist":{"shasum":"6a8a785430bfc321e537f0780b25e8f4012a6a21","tarball":"https://registry.npmjs.org/each/-/each-0.0.5.tgz"},"maintainers":[{"name":"david","email":"david@adaltas.com"}],"directories":{}},"0.0.6":{"name":"each","version":"0.0.6","description":"Chained and parallel async iterator in one elegant function","author":{"name":"David Worms","email":"david@adaltas.com"},"contributors":[{"name":"David Worms","email":"david@adaltas.com"}],"dependencies":{"coffee-script":"latest"},"engines":{"node":">= 0.4.0"},"keywords":["control flow","asynchronous","array","object","each"],"repository":{"type":"git","url":"git://github.com/wdavidw/node-each.git"},"_npmUser":{"name":"david","email":"david@adaltas.com"},"_id":"each@0.0.6","devDependencies":{},"_engineSupported":true,"_npmVersion":"1.0.105","_nodeVersion":"v0.6.1","_defaultsLoaded":true,"dist":{"shasum":"417dd8e22929d5b8be4dc1e12f94f6c19620ec24","tarball":"https://registry.npmjs.org/each/-/each-0.0.6.tgz"},"maintainers":[{"name":"david","email":"david@adaltas.com"}],"directories":{}},"0.0.7":{"name":"each","version":"0.0.7","description":"Chained and parallel async iterator in one elegant function","author":{"name":"David Worms","email":"david@adaltas.com"},"contributors":[{"name":"David Worms","email":"david@adaltas.com"}],"dependencies":{"coffee-script":"latest"},"engines":{"node":">= 0.4.0"},"keywords":["control flow","asynchronous","array","object","each"],"repository":{"type":"git","url":"git://github.com/wdavidw/node-each.git"},"_npmUser":{"name":"david","email":"david@adaltas.com"},"_id":"each@0.0.7","devDependencies":{},"_engineSupported":true,"_npmVersion":"1.0.105","_nodeVersion":"v0.6.1","_defaultsLoaded":true,"dist":{"shasum":"1f5450fab5c586275e5ce1169619124f6bd64836","tarball":"https://registry.npmjs.org/each/-/each-0.0.7.tgz"},"maintainers":[{"name":"david","email":"david@adaltas.com"}],"directories":{}},"0.0.8":{"name":"each","version":"0.0.8","description":"Chained and parallel async iterator in one elegant function","author":{"name":"David Worms","email":"david@adaltas.com"},"contributors":[{"name":"David Worms","email":"david@adaltas.com"}],"dependencies":{"coffee-script":"latest"},"engines":{"node":">= 0.4.0"},"keywords":["control flow","asynchronous","array","object","each"],"repository":{"type":"git","url":"git://github.com/wdavidw/node-each.git"},"_npmUser":{"name":"david","email":"david@adaltas.com"},"_id":"each@0.0.8","devDependencies":{},"_engineSupported":true,"_npmVersion":"1.0.105","_nodeVersion":"v0.6.1","_defaultsLoaded":true,"dist":{"shasum":"0956e4dc538d716178f8108a534415867ef907d6","tarball":"https://registry.npmjs.org/each/-/each-0.0.8.tgz"},"maintainers":[{"name":"david","email":"david@adaltas.com"}],"directories":{}},"0.0.9":{"name":"each","version":"0.0.9","description":"Chained and parallel async iterator in one elegant function","author":{"name":"David Worms","email":"david@adaltas.com"},"contributors":[{"name":"David Worms","email":"david@adaltas.com"}],"dependencies":{"coffee-script":"latest"},"engines":{"node":">= 0.4.0"},"keywords":["control flow","asynchronous","array","object","each"],"repository":{"type":"git","url":"git://github.com/wdavidw/node-each.git"},"_npmUser":{"name":"david","email":"david@adaltas.com"},"_id":"each@0.0.9","devDependencies":{},"_engineSupported":true,"_npmVersion":"1.1.0-beta-10","_nodeVersion":"v0.6.7","_defaultsLoaded":true,"dist":{"shasum":"4d224b4a948634a6cdc06ee02080e85e5d76a565","tarball":"https://registry.npmjs.org/each/-/each-0.0.9.tgz"},"maintainers":[{"name":"david","email":"david@adaltas.com"}],"directories":{}},"0.1.0":{"name":"each","version":"0.1.0","description":"Chained and parallel async iterator in one elegant function","author":{"name":"David Worms","email":"david@adaltas.com"},"contributors":[{"name":"David Worms","email":"david@adaltas.com"}],"dependencies":{"coffee-script":"latest"},"devDependencies":{"should":"latest","mocha":"latest"},"engines":{"node":">= 0.4.0"},"keywords":["control flow","asynchronous","array","object","each"],"repository":{"type":"git","url":"git://github.com/wdavidw/node-each.git"},"_npmUser":{"name":"david","email":"david@adaltas.com"},"_id":"each@0.1.0","optionalDependencies":{},"_engineSupported":true,"_npmVersion":"1.1.1","_nodeVersion":"v0.6.11","_defaultsLoaded":true,"dist":{"shasum":"12404d3c5ebf7814686291bfe243ce3a4508e86d","tarball":"https://registry.npmjs.org/each/-/each-0.1.0.tgz"},"maintainers":[{"name":"david","email":"david@adaltas.com"}],"directories":{}},"0.1.1":{"name":"each","version":"0.1.1","description":"Chained and parallel async iterator in one elegant function","author":{"name":"David Worms","email":"david@adaltas.com"},"contributors":[{"name":"David Worms","email":"david@adaltas.com"}],"scripts":{"test":"make test"},"dependencies":{"coffee-script":"latest"},"devDependencies":{"should":"latest","mocha":"latest"},"engines":{"node":">= 0.4.0"},"keywords":["control flow","asynchronous","array","object","each"],"repository":{"type":"git","url":"git://github.com/wdavidw/node-each.git"},"_npmUser":{"name":"david","email":"david@adaltas.com"},"_id":"each@0.1.1","optionalDependencies":{},"_engineSupported":true,"_npmVersion":"1.1.21","_nodeVersion":"v0.6.18","_defaultsLoaded":true,"dist":{"shasum":"712766e0084069c615275321a7ed5a9c83abd720","tarball":"https://registry.npmjs.org/each/-/each-0.1.1.tgz"},"maintainers":[{"name":"david","email":"david@adaltas.com"}],"directories":{}},"0.1.2":{"name":"each","version":"0.1.2","description":"Chained and parallel async iterator in one elegant function","author":{"name":"David Worms","email":"david@adaltas.com"},"contributors":[{"name":"David Worms","email":"david@adaltas.com"}],"scripts":{"test":"make test"},"dependencies":{"coffee-script":"latest"},"devDependencies":{"should":"latest","mocha":"latest"},"engines":{"node":">= 0.4.0"},"keywords":["control flow","asynchronous","array","object","each"],"repository":{"type":"git","url":"https://github.com/wdavidw/node-each.git"},"_id":"each@0.1.2","dist":{"shasum":"a85be8f8c86a28c33f7fdc1997325c8d34530d26","tarball":"https://registry.npmjs.org/each/-/each-0.1.2.tgz"},"maintainers":[{"name":"david","email":"david@adaltas.com"}],"directories":{}},"0.1.3":{"name":"each","version":"0.1.3","description":"Chained and parallel async iterator in one elegant function","author":{"name":"David Worms","email":"david@adaltas.com"},"contributors":[{"name":"David Worms","email":"david@adaltas.com"}],"scripts":{"test":"make test"},"devDependencies":{"coffee-script":"latest","should":"latest","mocha":"latest"},"engines":{"node":">= 0.4.0"},"keywords":["control flow","asynchronous","array","object","each"],"repository":{"type":"git","url":"https://github.com/wdavidw/node-each.git"},"_id":"each@0.1.3","dist":{"shasum":"c782e5b3dcaeb6727bfea41a79803f215b834702","tarball":"https://registry.npmjs.org/each/-/each-0.1.3.tgz"},"maintainers":[{"name":"david","email":"david@adaltas.com"}],"directories":{}},"0.1.4":{"name":"each","version":"0.1.4","description":"Chained and parallel async iterator in one elegant function","author":{"name":"David Worms","email":"david@adaltas.com"},"contributors":[{"name":"David Worms","email":"david@adaltas.com"}],"scripts":{"test":"make test"},"devDependencies":{"coffee-script":"latest","should":"latest","mocha":"latest"},"engines":{"node":">= 0.4.0"},"keywords":["control flow","asynchronous","array","object","each"],"repository":{"type":"git","url":"https://github.com/wdavidw/node-each.git"},"_id":"each@0.1.4","dist":{"shasum":"d361de9ec7b482ff99b6263008607d80f500b5ce","tarball":"https://registry.npmjs.org/each/-/each-0.1.4.tgz"},"maintainers":[{"name":"david","email":"david@adaltas.com"}],"directories":{}},"0.2.0":{"name":"each","version":"0.2.0","description":"Chained and parallel async iterator in one elegant function","author":{"name":"David Worms","email":"david@adaltas.com"},"contributors":[{"name":"David Worms","email":"david@adaltas.com"}],"scripts":{"test":"make test"},"devDependencies":{"coffee-script":"latest","should":"latest","mocha":"latest"},"engines":{"node":">= 0.4.0"},"keywords":["control flow","asynchronous","array","object","each"],"repository":{"type":"git","url":"https://github.com/wdavidw/node-each.git"},"_id":"each@0.2.0","dist":{"shasum":"ddbd36a3a1e48254734c7ce98bf5bf7c09d1a4d2","tarball":"https://registry.npmjs.org/each/-/each-0.2.0.tgz"},"maintainers":[{"name":"david","email":"david@adaltas.com"}],"directories":{}},"0.2.1":{"name":"each","version":"0.2.1","description":"Chained and parallel async iterator in one elegant function","homepage":"http://www.adaltas.com/projects/node-each/","author":{"name":"David Worms","email":"david@adaltas.com"},"contributors":[{"name":"David Worms","email":"david@adaltas.com"}],"scripts":{"test":"make test"},"devDependencies":{"coffee-script":"latest","should":"latest","mocha":"latest"},"engines":{"node":">= 0.4.0"},"keywords":["control flow","asynchronous","array","object","each"],"repository":{"type":"git","url":"https://github.com/wdavidw/node-each.git"},"_id":"each@0.2.1","dist":{"shasum":"839daa3c07cc3e1792908480167ca0d972cc3f6a","tarball":"https://registry.npmjs.org/each/-/each-0.2.1.tgz"},"maintainers":[{"name":"david","email":"david@adaltas.com"}],"directories":{}},"0.3.0":{"name":"each","version":"0.3.0","description":"Chained and parallel async iterator in one elegant function","homepage":"http://www.adaltas.com/projects/node-each/","author":{"name":"David Worms","email":"david@adaltas.com"},"contributors":[{"name":"David Worms","email":"david@adaltas.com"}],"scripts":{"test":"make test"},"devDependencies":{"coffee-script":"latest","should":"latest","mocha":"latest"},"engines":{"node":">= 0.4.0"},"keywords":["control flow","asynchronous","array","object","each"],"repository":{"type":"git","url":"https://github.com/wdavidw/node-each.git"},"_id":"each@0.3.0","dist":{"shasum":"be5efdd5eb14b5d11f339e45f035b4484dacc7a1","tarball":"https://registry.npmjs.org/each/-/each-0.3.0.tgz"},"maintainers":[{"name":"david","email":"david@adaltas.com"}],"directories":{}},"0.3.1":{"name":"each","version":"0.3.1","description":"Chained and parallel async iterator in one elegant function","homepage":"http://www.adaltas.com/projects/node-each/","author":{"name":"David Worms","email":"david@adaltas.com"},"contributors":[{"name":"David Worms","email":"david@adaltas.com"}],"scripts":{"test":"make test"},"devDependencies":{"coffee-script":"latest","should":"latest","mocha":"latest"},"engines":{"node":">= 0.4.0"},"keywords":["control flow","asynchronous","array","object","each"],"repository":{"type":"git","url":"https://github.com/wdavidw/node-each.git"},"_id":"each@0.3.1","dist":{"shasum":"92cf8cd7b97b4334eaefdf863cab1dd114f1e7fa","tarball":"https://registry.npmjs.org/each/-/each-0.3.1.tgz"},"maintainers":[{"name":"david","email":"david@adaltas.com"}],"directories":{}},"0.3.2":{"name":"each","version":"0.3.2","description":"Chained and parallel async iterator in one elegant function","homepage":"http://www.adaltas.com/projects/node-each/","author":{"name":"David Worms","email":"david@adaltas.com"},"contributors":[{"name":"David Worms","email":"david@adaltas.com"}],"scripts":{"test":"make test"},"dependencies":{"glob":"latest"},"devDependencies":{"coffee-script":"latest","should":"latest","mocha":"latest"},"engines":{"node":">= 0.4.0"},"keywords":["control flow","asynchronous","array","object","each"],"repository":{"type":"git","url":"https://github.com/wdavidw/node-each.git"},"_id":"each@0.3.2","dist":{"shasum":"622fb8d139ed9b234223c8293a1493f762d8a66d","tarball":"https://registry.npmjs.org/each/-/each-0.3.2.tgz"},"maintainers":[{"name":"david","email":"david@adaltas.com"}],"directories":{}},"0.3.3":{"name":"each","version":"0.3.3","description":"Chained and parallel async iterator in one elegant function","homepage":"http://www.adaltas.com/projects/node-each/","author":{"name":"David Worms","email":"david@adaltas.com"},"contributors":[{"name":"David Worms","email":"david@adaltas.com"}],"scripts":{"test":"make test"},"dependencies":{"glob":"latest"},"devDependencies":{"coffee-script":"latest","should":"latest","mocha":"latest"},"engines":{"node":">= 0.4.0"},"keywords":["control flow","asynchronous","array","object","each"],"repository":{"type":"git","url":"https://github.com/wdavidw/node-each.git"},"_id":"each@0.3.3","dist":{"shasum":"222d9ec5858cafb9556efef1c1e7dcaba196ea85","tarball":"https://registry.npmjs.org/each/-/each-0.3.3.tgz"},"maintainers":[{"name":"david","email":"david@adaltas.com"}],"directories":{}},"0.3.4":{"name":"each","version":"0.3.4","description":"Chained and parallel async iterator in one elegant function","homepage":"http://www.adaltas.com/projects/node-each/","author":{"name":"David Worms","email":"david@adaltas.com"},"contributors":[{"name":"David Worms","email":"david@adaltas.com"}],"scripts":{"test":"make test"},"dependencies":{"glob":"latest"},"devDependencies":{"coffee-script":"latest","should":"latest","mocha":"latest"},"engines":{"node":">= 0.4.0"},"keywords":["control flow","asynchronous","array","object","each"],"repository":{"type":"git","url":"https://github.com/wdavidw/node-each.git"},"_id":"each@0.3.4","dist":{"shasum":"62275852dc9037fa8b06d119f33eca0568e44023","tarball":"https://registry.npmjs.org/each/-/each-0.3.4.tgz"},"maintainers":[{"name":"david","email":"david@adaltas.com"}],"directories":{}},"0.4.1":{"name":"each","version":"0.4.1","description":"Chained and parallel async iterator in one elegant function","homepage":"http://www.adaltas.com/projects/node-each/","author":{"name":"David Worms","email":"david@adaltas.com"},"contributors":[{"name":"David Worms","email":"david@adaltas.com"}],"scripts":{"test":"make test"},"dependencies":{"glob":"latest"},"devDependencies":{"coffee-script":"latest","should":"latest","mocha":"latest"},"engines":{"node":">= 0.4.0"},"keywords":["control flow","asynchronous","array","object","each"],"repository":{"type":"git","url":"https://github.com/wdavidw/node-each.git"},"_id":"each@0.4.1","dist":{"shasum":"38ce3395f1ca7d5e38fd65d221b46d240f009761","tarball":"https://registry.npmjs.org/each/-/each-0.4.1.tgz"},"_from":".","_npmVersion":"1.2.3","_npmUser":{"name":"david","email":"david@adaltas.com"},"maintainers":[{"name":"david","email":"david@adaltas.com"}],"directories":{}},"0.4.2":{"name":"each","version":"0.4.2","description":"Chained and parallel async iterator in one elegant function","homepage":"http://www.adaltas.com/projects/node-each/","author":{"name":"David Worms","email":"david@adaltas.com"},"contributors":[{"name":"David Worms","email":"david@adaltas.com"}],"scripts":{"test":"make test"},"dependencies":{"glob":"latest"},"devDependencies":{"coffee-script":"latest","should":"latest","mocha":"latest"},"engines":{"node":">= 0.4.0"},"keywords":["control flow","asynchronous","array","object","each"],"repository":{"type":"git","url":"https://github.com/wdavidw/node-each.git"},"_id":"each@0.4.2","dist":{"shasum":"2997ca447016f7f9ce5e88376716a99124a4ffee","tarball":"https://registry.npmjs.org/each/-/each-0.4.2.tgz"},"_from":".","_npmVersion":"1.2.11","_npmUser":{"name":"david","email":"david@adaltas.com"},"maintainers":[{"name":"david","email":"david@adaltas.com"}],"directories":{}},"0.4.3":{"name":"each","version":"0.4.3","description":"Chained and parallel async iterator in one elegant function","homepage":"http://www.adaltas.com/projects/node-each/","author":{"name":"David Worms","email":"david@adaltas.com"},"contributors":[{"name":"David Worms","email":"david@adaltas.com"}],"scripts":{"test":"make test"},"dependencies":{"glob":"latest"},"devDependencies":{"coffee-script":"latest","should":"latest","mocha":"latest"},"engines":{"node":">= 0.4.0"},"keywords":["control flow","asynchronous","array","object","each"],"repository":{"type":"git","url":"https://github.com/wdavidw/node-each.git"},"_id":"each@0.4.3","dist":{"shasum":"e1e5df9e32ad31ed77457e3699cd2780fad00de8","tarball":"https://registry.npmjs.org/each/-/each-0.4.3.tgz"},"_from":".","_npmVersion":"1.2.11","_npmUser":{"name":"david","email":"david@adaltas.com"},"maintainers":[{"name":"david","email":"david@adaltas.com"}],"directories":{}},"0.4.4":{"name":"each","version":"0.4.4","description":"Chained and parallel async iterator in one elegant function","homepage":"http://www.adaltas.com/projects/node-each/","author":{"name":"David Worms","email":"david@adaltas.com"},"contributors":[{"name":"David Worms","email":"david@adaltas.com"}],"scripts":{"test":"make test"},"dependencies":{"glob":"latest"},"devDependencies":{"coffee-script":"latest","should":"latest","mocha":"latest"},"engines":{"node":">= 0.4.0"},"keywords":["control flow","asynchronous","array","object","each"],"repository":{"type":"git","url":"https://github.com/wdavidw/node-each.git"},"_id":"each@0.4.4","dist":{"shasum":"64c4fddab32bfe4372de64755607b2527f49796f","tarball":"https://registry.npmjs.org/each/-/each-0.4.4.tgz"},"_from":".","_npmVersion":"1.2.18","_npmUser":{"name":"david","email":"david@adaltas.com"},"maintainers":[{"name":"david","email":"david@adaltas.com"}],"directories":{}},"0.4.5":{"name":"each","version":"0.4.5","description":"Chained and parallel async iterator in one elegant function","homepage":"http://www.adaltas.com/projects/node-each/","author":{"name":"David Worms","email":"david@adaltas.com"},"contributors":[{"name":"David Worms","email":"david@adaltas.com"}],"scripts":{"test":"make test"},"dependencies":{"glob":"latest"},"devDependencies":{"coffee-script":"latest","should":"latest","mocha":"latest"},"engines":{"node":">= 0.4.0"},"keywords":["control flow","asynchronous","array","object","each"],"repository":{"type":"git","url":"https://github.com/wdavidw/node-each.git"},"_id":"each@0.4.5","dist":{"shasum":"b3193a606b5257330d9473ae31a2f75996127600","tarball":"https://registry.npmjs.org/each/-/each-0.4.5.tgz"},"_from":".","_npmVersion":"1.2.11","_npmUser":{"name":"david","email":"david@adaltas.com"},"maintainers":[{"name":"david","email":"david@adaltas.com"}],"directories":{}},"0.4.6":{"name":"each","version":"0.4.6","description":"Chained and parallel async iterator in one elegant function","homepage":"http://www.adaltas.com/projects/node-each/","author":{"name":"David Worms","email":"david@adaltas.com"},"contributors":[{"name":"David Worms","email":"david@adaltas.com"}],"scripts":{"test":"make test"},"dependencies":{"glob":"latest"},"devDependencies":{"coffee-script":"latest","should":"latest","mocha":"latest"},"engines":{"node":">= 0.4.0"},"keywords":["control flow","asynchronous","array","object","each"],"repository":{"type":"git","url":"https://github.com/wdavidw/node-each.git"},"bugs":{"url":"https://github.com/wdavidw/node-each/issues"},"_id":"each@0.4.6","dist":{"shasum":"5979f22cda0d52e84e5ef47fd409440d93779812","tarball":"https://registry.npmjs.org/each/-/each-0.4.6.tgz"},"_from":".","_npmVersion":"1.2.24","_npmUser":{"name":"david","email":"david@adaltas.com"},"maintainers":[{"name":"david","email":"david@adaltas.com"}],"directories":{}},"0.4.8":{"name":"each","version":"0.4.8","description":"Chained and parallel async iterator in one elegant function","homepage":"http://www.adaltas.com/projects/node-each/","author":{"name":"David Worms","email":"david@adaltas.com"},"contributors":[{"name":"David Worms","email":"david@adaltas.com"}],"scripts":{"test":"make test"},"dependencies":{"glob":"latest"},"devDependencies":{"coffee-script":"latest","should":"latest","mocha":"latest"},"engines":{"node":">= 0.4.0"},"keywords":["control flow","asynchronous","array","object","each"],"repository":{"type":"git","url":"https://github.com/wdavidw/node-each.git"},"bugs":{"url":"https://github.com/wdavidw/node-each/issues"},"_id":"each@0.4.8","dist":{"shasum":"a01a54c046b14cf64f24dd91c650d82231e95d31","tarball":"https://registry.npmjs.org/each/-/each-0.4.8.tgz"},"_from":".","_npmVersion":"1.2.24","_npmUser":{"name":"david","email":"david@adaltas.com"},"maintainers":[{"name":"david","email":"david@adaltas.com"}],"directories":{}},"0.4.9":{"name":"each","version":"0.4.9","description":"Chained and parallel async iterator in one elegant function","homepage":"http://www.adaltas.com/projects/node-each/","author":{"name":"David Worms","email":"david@adaltas.com"},"contributors":[{"name":"David Worms","email":"david@adaltas.com"}],"scripts":{"test":"make test"},"dependencies":{"glob":"latest"},"devDependencies":{"coffee-script":"latest","should":"latest","mocha":"latest"},"engines":{"node":">= 0.4.0"},"keywords":["control flow","asynchronous","array","object","each"],"repository":{"type":"git","url":"https://github.com/wdavidw/node-each.git"},"bugs":{"url":"https://github.com/wdavidw/node-each/issues"},"_id":"each@0.4.9","dist":{"shasum":"97d1c419f390bb40c333517bfee48cb74d8a0ad1","tarball":"https://registry.npmjs.org/each/-/each-0.4.9.tgz"},"_from":".","_npmVersion":"1.3.14","_npmUser":{"name":"david","email":"david@adaltas.com"},"maintainers":[{"name":"david","email":"david@adaltas.com"}],"directories":{}},"0.5.0":{"name":"each","version":"0.5.0","description":"Chained and parallel async iterator in one elegant function","homepage":"http://www.adaltas.com/projects/node-each/","author":{"name":"David Worms","email":"david@adaltas.com"},"contributors":[{"name":"David Worms","email":"david@adaltas.com"}],"dependencies":{"glob":"latest"},"devDependencies":{"coffee-script":"latest","should":"latest","mocha":"latest"},"engines":{"node":">= 0.9.0"},"keywords":["control flow","asynchronous","array","object","each"],"repository":{"type":"git","url":"https://github.com/wdavidw/node-each.git"},"scripts":{"coffee":"coffee -b -o lib src","pretest":"coffee -b -o lib src","test":"NODE_ENV=test ./node_modules/.bin/mocha --compilers coffee:coffee-script/register --reporter dot"},"gitHead":"ee808dc47d0eff08bf4194ea4e69fca1e9e4723b","bugs":{"url":"https://github.com/wdavidw/node-each/issues"},"_id":"each@0.5.0","_shasum":"8b8683e4cf1c3a4af0e3b0885f41e0fa0b5db76e","_from":".","_npmVersion":"1.4.28","_npmUser":{"name":"david","email":"david@adaltas.com"},"maintainers":[{"name":"david","email":"david@adaltas.com"}],"dist":{"shasum":"8b8683e4cf1c3a4af0e3b0885f41e0fa0b5db76e","tarball":"https://registry.npmjs.org/each/-/each-0.5.0.tgz"},"directories":{}},"0.5.1":{"name":"each","version":"0.5.1","description":"Chained and parallel async iterator in one elegant function","homepage":"http://www.adaltas.com/projects/node-each/","author":{"name":"David Worms","email":"david@adaltas.com"},"license":"BSD-3-Clause","contributors":[{"name":"David Worms","email":"david@adaltas.com"}],"dependencies":{"glob":"5.0.3"},"devDependencies":{"coffee-script":"1.9.1","should":"5.2.0","mocha":"2.2.4"},"engines":{"node":">= 0.9.0"},"keywords":["control flow","asynchronous","array","object","each"],"repository":{"type":"git","url":"https://github.com/wdavidw/node-each.git"},"scripts":{"coffee":"coffee -b -o lib src","pretest":"coffee -b -o lib src","test":"NODE_ENV=test ./node_modules/.bin/mocha --compilers coffee:coffee-script/register --reporter dot"},"gitHead":"2779ca74df01adf79e8006d318183a2fa27ce27b","bugs":{"url":"https://github.com/wdavidw/node-each/issues"},"_id":"each@0.5.1","_shasum":"4685bb4dee8e3ffdb2d2f75af7ba731f68200f6b","_from":".","_npmVersion":"1.4.28","_npmUser":{"name":"david","email":"david@adaltas.com"},"maintainers":[{"name":"david","email":"david@adaltas.com"}],"dist":{"shasum":"4685bb4dee8e3ffdb2d2f75af7ba731f68200f6b","tarball":"https://registry.npmjs.org/each/-/each-0.5.1.tgz"},"directories":{}},"0.5.2":{"name":"each","version":"0.5.2","description":"Chained and parallel async iterator in one elegant function","homepage":"http://www.adaltas.com/projects/node-each/","author":{"name":"David Worms","email":"david@adaltas.com"},"license":"BSD-3-Clause","contributors":[{"name":"David Worms","email":"david@adaltas.com"}],"dependencies":{"glob":"5.0.10"},"devDependencies":{"coffee-script":"1.9.3","should":"6.0.3","mocha":"2.2.5"},"engines":{"node":">= 0.9.0"},"keywords":["control flow","asynchronous","array","object","each"],"repository":{"type":"git","url":"https://github.com/wdavidw/node-each.git"},"scripts":{"coffee":"coffee -b -o lib src","pretest":"coffee -b -o lib src","test":"NODE_ENV=test ./node_modules/.bin/mocha --compilers coffee:coffee-script/register --reporter dot"},"gitHead":"39076d7d385b04f4599b7ce835191eff2751ba68","bugs":{"url":"https://github.com/wdavidw/node-each/issues"},"_id":"each@0.5.2","_shasum":"479551023c557d17eab00fd81d82bf5fc0184c02","_from":".","_npmVersion":"1.4.28","_npmUser":{"name":"david","email":"david@adaltas.com"},"maintainers":[{"name":"david","email":"david@adaltas.com"}],"dist":{"shasum":"479551023c557d17eab00fd81d82bf5fc0184c02","tarball":"https://registry.npmjs.org/each/-/each-0.5.2.tgz"},"directories":{}},"0.6.0":{"name":"each","version":"0.6.0","description":"Chained and parallel async iterator in one elegant function","homepage":"http://www.adaltas.com/projects/node-each/","author":{"name":"David Worms","email":"david@adaltas.com"},"license":"BSD-3-Clause","contributors":[{"name":"David Worms","email":"david@adaltas.com"}],"dependencies":{"glob":"7.0.0"},"devDependencies":{"coffee-script":"1.10.0","should":"8.2.2","mocha":"2.4.5"},"engines":{"node":">= 0.9.0"},"main":"./lib/index","keywords":["control flow","asynchronous","array","object","each"],"repository":{"type":"git","url":"https://github.com/wdavidw/node-each.git"},"scripts":{"coffee":"coffee -b -o lib src","pretest":"coffee -b -o lib src","test":"NODE_ENV=test ./node_modules/.bin/mocha --compilers coffee:coffee-script/register --reporter dot"},"gitHead":"778fa63d31abf9a8a3f24d0288d37ae729a909ca","bugs":{"url":"https://github.com/wdavidw/node-each/issues"},"_id":"each@0.6.0","_shasum":"5cec18adba6589b31cebbcea905fc2398c993de3","_from":".","_npmVersion":"3.6.0","_nodeVersion":"5.6.0","_npmUser":{"name":"david","email":"david@adaltas.com"},"maintainers":[{"name":"david","email":"david@adaltas.com"}],"dist":{"shasum":"5cec18adba6589b31cebbcea905fc2398c993de3","tarball":"https://registry.npmjs.org/each/-/each-0.6.0.tgz"},"_npmOperationalInternal":{"host":"packages-12-west.internal.npmjs.com","tmp":"tmp/each-0.6.0.tgz_1457997154356_0.8024375035893172"},"directories":{}},"0.6.1":{"name":"each","version":"0.6.1","description":"Chained and parallel async iterator in one elegant function","homepage":"http://www.adaltas.com/projects/node-each/","author":{"name":"David Worms","email":"david@adaltas.com"},"license":"BSD-3-Clause","contributors":[{"name":"David Worms","email":"david@adaltas.com"}],"dependencies":{"glob":"~7.0.0"},"devDependencies":{"coffee-script":"1.10.0","should":"~8.3.1","mocha":"~2.4.5"},"engines":{"node":">= 0.9.0"},"main":"./lib/index","keywords":["control flow","asynchronous","array","object","each"],"repository":{"type":"git","url":"git+https://github.com/wdavidw/node-each.git"},"scripts":{"coffee":"coffee -b -o lib src","pretest":"coffee -b -o lib src","test":"NODE_ENV=test ./node_modules/.bin/mocha --compilers coffee:coffee-script/register --reporter dot"},"gitHead":"b4513b2409c6dc0c56d978f5cf05b710a9a1e488","bugs":{"url":"https://github.com/wdavidw/node-each/issues"},"_id":"each@0.6.1","_shasum":"1181cc47933882055a590f70ae78c1b11f1b8865","_from":".","_npmVersion":"3.8.7","_nodeVersion":"6.0.0","_npmUser":{"name":"david","email":"david@adaltas.com"},"maintainers":[{"name":"david","email":"david@adaltas.com"}],"dist":{"shasum":"1181cc47933882055a590f70ae78c1b11f1b8865","tarball":"https://registry.npmjs.org/each/-/each-0.6.1.tgz"},"_npmOperationalInternal":{"host":"packages-12-west.internal.npmjs.com","tmp":"tmp/each-0.6.1.tgz_1461781368395_0.8626791618298739"},"directories":{}}},"maintainers":[{"name":"david","email":"david@adaltas.com"}],"time":{"modified":"2017-04-02T19:23:05.145Z","created":"2011-10-04T10:57:07.151Z","0.0.1":"2011-10-04T10:57:09.540Z","0.0.2":"2011-10-29T13:15:45.264Z","0.0.3":"2011-11-15T21:29:33.479Z","0.0.4":"2011-11-17T12:30:33.286Z","0.0.5":"2011-11-17T17:19:18.765Z","0.0.6":"2011-11-22T09:56:10.468Z","0.0.7":"2011-11-28T12:10:59.526Z","0.0.8":"2011-11-28T13:22:08.758Z","0.0.9":"2012-02-16T14:53:08.311Z","0.1.0":"2012-03-10T17:33:09.501Z","0.1.1":"2012-06-10T22:34:26.220Z","0.1.2":"2012-11-12T15:39:58.051Z","0.1.3":"2012-11-12T16:05:22.739Z","0.1.4":"2012-11-13T13:26:14.582Z","0.2.0":"2012-11-13T13:36:21.215Z","0.2.1":"2012-11-29T17:54:20.689Z","0.3.0":"2012-12-01T19:47:27.153Z","0.3.1":"2012-12-01T20:27:58.491Z","0.3.2":"2012-12-05T21:55:02.631Z","0.3.3":"2012-12-11T18:20:28.313Z","0.3.4":"2013-01-23T14:49:37.241Z","0.4.1":"2013-02-09T21:22:12.593Z","0.4.2":"2013-03-27T22:29:10.940Z","0.4.3":"2013-03-28T22:36:31.334Z","0.4.4":"2013-05-16T15:24:57.444Z","0.4.5":"2013-05-22T21:07:39.057Z","0.4.6":"2013-06-03T12:54:50.423Z","0.4.8":"2013-06-16T21:35:25.153Z","0.4.9":"2014-02-04T13:06:38.949Z","0.5.0":"2015-02-16T16:14:04.153Z","0.5.1":"2015-06-09T09:55:59.140Z","0.5.2":"2015-06-09T14:43:12.885Z","0.6.0":"2016-03-14T23:12:36.940Z","0.6.1":"2016-04-27T18:22:51.069Z"},"author":{"name":"David Worms","email":"david@adaltas.com"},"repository":{"type":"git","url":"git+https://github.com/wdavidw/node-each.git"},"users":{"david":true,"bradcozine":true,"loominade":true,"alfeo92":true},"readme":"[![Build Status](https://secure.travis-ci.org/wdavidw/node-each.png)](http://travis-ci.org/wdavidw/node-each)\n\n<pre style=\"font-family:courier\">\n _   _           _        ______           _     \n| \\ | |         | |      |  ____|         | |    \n|  \\| | ___   __| | ___  | |__   __ _  ___| |__  \n| . ` |/ _ \\ / _` |/ _ \\ |  __| / _` |/ __| '_ \\ \n| |\\  | (_) | (_| |  __/ | |___| (_| | (__| | | |\n|_| \\_|\\___/ \\__,_|\\___| |______\\__,_|\\___|_| |_| New BSD License\n</pre>\n\n\n[Full documentation for the Each is available here](http://www.adaltas.com/projects/node-each/).\n\nNote, for user of versions 0.2.x and below, arguments of the item callback have changed. See [the documentation](http://www.adaltas.com/projects/node-each/) for additionnal information.\n\nNode Each is a single elegant function to iterate asynchronously over elements \nboth in `sequential`, `parallel` and `concurrent` mode.\n\n## Example\n\n```javascript\neach( [{id: 1}, {id: 2}, {id: 3}] )\n.call( function(element, index, next){\n  console.log('element: ', element, '@', index);\n  setTimeout(next, 500);\n})\n.then( function(err){\n  console.log(err ? err.message : 'Done');\n});\n```\n\n## Development\n\nNode Each comes with a few example, all present in the \"samples\" folder. Here's how you may run each of them :\n\n```bash\nnode samples/array_concurrent.js\nnode samples/array_parallel.js\nnode samples/array_sequential.js\nnode samples/object_concurrent.js\nnode samples/object_sequential.js\nnode samples/readable_stream.js\n```\n\nTests are executed with mocha. To install it, simple run `npm install`, it will install\nmocha and its dependencies in your project \"node_modules\" directory.\n\n```bash\nmake test\n```\n","readmeFilename":"README.md","homepage":"http://www.adaltas.com/projects/node-each/","keywords":["control flow","asynchronous","array","object","each"],"contributors":[{"name":"David Worms","email":"david@adaltas.com"}],"bugs":{"url":"https://github.com/wdavidw/node-each/issues"},"license":"BSD-3-Clause","_attachments":{},"_etag":"W/\"58e14f99-8b84\"","_lastModified":"Sun, 02 Apr 2017 19:23:05 GMT"}